{
  "generator-jhipster": {
    "applicationType": "microservice",
    "authenticationType": "oauth2",
    "baseName": "backEnd",
    "buildTool": "maven",
    "cacheProvider": "no",
    "clientFramework": "angular",
    "clientTestFrameworks": [],
    "clientTheme": "none",
    "creationTimestamp": 1742134969751,
    "databaseType": "sql",
    "devDatabaseType": "postgresql",
    "enableHibernateCache": null,
    "enableTranslation": true,
    "entities": [],
    "feignClient": false,
    "jhipsterVersion": "8.9.0",
    "languages": ["pt-br", "en"],
    "microfrontend": null,
    "microfrontends": [],
    "monorepository": true,
    "nativeLanguage": "pt-br",
    "packageName": "com.mycompany.myapp",
    "prodDatabaseType": "postgresql",
    "reactive": false,
    "serverPort": 8081,
    "serviceDiscoveryType": "eureka",
    "skipCommitHook": true,
    "skipUserManagement": true,
    "syncUserWithIdp": true,
    "testFrameworks": [],
    "withAdminUi": false
  }
}
